create_dagster/__init__.py
create_dagster/py.typed
create_dagster/scaffold.py
create_dagster/version.py
create_dagster/version_check.py
create_dagster/cli/__init__.py
create_dagster/cli/scaffold.py
create_dagster/templates/PROJECT_NAME_PLACEHOLDER/.gitignore
create_dagster/templates/PROJECT_NAME_PLACEHOLDER/README.md.jinja
create_dagster/templates/PROJECT_NAME_PLACEHOLDER/pyproject.toml.jinja
create_dagster/templates/PROJECT_NAME_PLACEHOLDER/.dg/telemetry.yaml.jinja
create_dagster/templates/PROJECT_NAME_PLACEHOLDER/src/PROJECT_NAME_PLACEHOLDER/__init__.py
create_dagster/templates/PROJECT_NAME_PLACEHOLDER/src/PROJECT_NAME_PLACEHOLDER/definitions.py.jinja
create_dagster/templates/PROJECT_NAME_PLACEHOLDER/src/PROJECT_NAME_PLACEHOLDER/defs/.gitkeep
create_dagster/templates/PROJECT_NAME_PLACEHOLDER/src/PROJECT_NAME_PLACEHOLDER/defs/__init__.py
create_dagster/templates/PROJECT_NAME_PLACEHOLDER/tests/__init__.py
create_dagster/templates/WORKSPACE_NAME_PLACEHOLDER/dg.toml.jinja
create_dagster/templates/WORKSPACE_NAME_PLACEHOLDER/deployments/local/pyproject.toml.jinja
create_dagster/templates/WORKSPACE_NAME_PLACEHOLDER/projects/.gitkeep
create_dagster-1.12.13.dist-info/licenses/LICENSE
create_dagster-1.12.13.dist-info/METADATA
create_dagster-1.12.13.dist-info/WHEEL
create_dagster-1.12.13.dist-info/entry_points.txt
create_dagster-1.12.13.dist-info/top_level.txt
create_dagster-1.12.13.dist-info/RECORD
