Metadata-Version: 2.4
Name: create-dagster
Version: 1.12.13
Summary: CLI for creating a new dg project or workspace.
Home-page: https://github.com/dagster-io/dagster/tree/master/python_modules/libraries/create-dagster
Author: Dagster Labs
Author-email: hello@dagsterlabs.com
License: Apache-2.0
Classifier: Programming Language :: Python :: 3.10
Classifier: Programming Language :: Python :: 3.11
Classifier: Programming Language :: Python :: 3.12
Classifier: Programming Language :: Python :: 3.13
Classifier: Programming Language :: Python :: 3.14
Classifier: License :: OSI Approved :: Apache Software License
Classifier: Operating System :: OS Independent
License-File: LICENSE
Requires-Dist: dagster-dg-core==1.12.13
Provides-Extra: test
Requires-Dist: pytest; extra == "test"
Requires-Dist: flaky; extra == "test"
Requires-Dist: psutil; extra == "test"
Dynamic: author
Dynamic: author-email
Dynamic: classifier
Dynamic: home-page
Dynamic: license
Dynamic: license-file
Dynamic: provides-extra
Dynamic: requires-dist
Dynamic: summary
